repleno/SKU.py
repleno/__init__.py
repleno/__main__.py
repleno/factory.py
repleno/order.py
repleno/utils.py
repleno-0.0.18.dist-info/METADATA
repleno-0.0.18.dist-info/WHEEL
repleno-0.0.18.dist-info/top_level.txt
repleno-0.0.18.dist-info/RECORD
